setup.py
cloudcmd/__init__.py
cloudcmd/floatingips.py
cloudcmd/graphite.py
cloudcmd/hypervisor.py
cloudcmd/instance.py
cloudcmd/main.py
cloudcmd/services.py
cloudcmd/tenants.py
cloudcmd/token.py
cloudcmd/version.py
cloudcmd/volumes.py
cloudcmd/zombie.py
cloudcmd.egg-info/PKG-INFO
cloudcmd.egg-info/SOURCES.txt
cloudcmd.egg-info/dependency_links.txt
cloudcmd.egg-info/entry_points.txt
cloudcmd.egg-info/not-zip-safe
cloudcmd.egg-info/requires.txt
cloudcmd.egg-info/top_level.txt