Metadata-Version: 1.2
Name: cloudcmd
Version: 2020.7.2
Summary: cloud command line tools
Home-page: https://github.com/Hawkgirl/cloudcmd/
Author: Hawkgirl
Maintainer: Hawkgril
Maintainer-email: hawkgirlgit@gmail.com
License: BSD
Platform: Any
